easy_bitrix/__init__.py
easy_bitrix/api_requestor.py
easy_bitrix/bitrix.py
easy_bitrix/bitrix_objects.py
easy_bitrix/common.py
easy_bitrix/dto.py
easy_bitrix/error.py
easy_bitrix/fields.py
easy_bitrix/http_client.py
easy_bitrix/logger.py
easy_bitrix/main.py
easy_bitrix/oauth.py
easy_bitrix/operations.py
easy_bitrix/options.py
easy_bitrix/parameters.py
easy_bitrix/response_object.py
easy_bitrix/test.py
easy_bitrix-0.1.18.dist-info/licenses/LICENSE
easy_bitrix-0.1.18.dist-info/METADATA
easy_bitrix-0.1.18.dist-info/WHEEL
easy_bitrix-0.1.18.dist-info/top_level.txt
easy_bitrix-0.1.18.dist-info/RECORD
