Metadata-Version: 2.4
Name: easy-bitrix
Version: 0.1.18
Summary: Python Library with easy API for Bitrix24 REST
Author: Alexsander Pavlov
Author-email: Alex Pavlov <yukiu217@gmail.com>
License-Expression: MIT
Project-URL: Homepage, https://github.com/sumaro2101/easy-bitrix
Requires-Python: >=3.8
License-File: LICENSE
Requires-Dist: httpx<0.29.0,>=0.28.1
Dynamic: author
Dynamic: license-file
